my_oauth_package/__init__.py
my_oauth_package/test.py
my_oauth_package-2.3.5.dist-info/LICENSE.txt
my_oauth_package-2.3.5.dist-info/METADATA
my_oauth_package-2.3.5.dist-info/WHEEL
my_oauth_package-2.3.5.dist-info/top_level.txt
my_oauth_package-2.3.5.dist-info/RECORD
