Metadata-Version: 2.1
Name: my_oauth_package
Version: 2.3.5
Summary: A package for handling Xecurify authentication
Author: Romit
Author-email: romitaherkar@gmail.com
Classifier: Programming Language :: Python :: 3
Classifier: License :: OSI Approved :: MIT License
Classifier: Operating System :: OS Independent
License-File: LICENSE.txt
Requires-Dist: cryptography
Requires-Dist: pyjwt
Requires-Dist: django
